MANIFEST.in
README.md
setup.cfg
setup.py
smarkov/__init__.py
smarkov/hmm.py
smarkov/markov.py
smarkov/utils.py
smarkov.egg-info/PKG-INFO
smarkov.egg-info/SOURCES.txt
smarkov.egg-info/dependency_links.txt
smarkov.egg-info/top_level.txt