Metadata-Version: 1.1
Name: smarkov
Version: 1.0
Summary: Simple Markov and HMM
Home-page: https://github.com/greenify/smarkov
Author: greenify
Author-email: greenify@gmail.com
License: MIT
Keywords: hmm markov
Platform: UNKNOWN
Classifier: Development Status :: 3 - Alpha
Classifier: Intended Audience :: Developers
Classifier: Intended Audience :: Science/Research
Classifier: Topic :: Scientific/Engineering :: Artificial Intelligence
Classifier: License :: OSI Approved :: MIT License
Classifier: Programming Language :: Python :: 3
Classifier: Programming Language :: Python :: 3.3
Classifier: Programming Language :: Python :: 3.4
Classifier: Programming Language :: Python :: 3.5
